py_fa_calendar.py
py_fa_calendar-0.1.0.dist-info/METADATA
py_fa_calendar-0.1.0.dist-info/WHEEL
py_fa_calendar-0.1.0.dist-info/top_level.txt
py_fa_calendar-0.1.0.dist-info/RECORD
