Metadata-Version: 2.4
Name: py_fa_calendar
Version: 0.1.0
Summary: A Persian calendar package and countdowns
Author: Mahan010
Requires-Python: >=3.6
Requires-Dist: datetime
